LICENSE.txt
MANIFEST.in
README.md
setup.cfg
setup.py
frase/__init__.py
frase/cli.py
frase/settings.py
frase/utils.py
frase.egg-info/PKG-INFO
frase.egg-info/SOURCES.txt
frase.egg-info/dependency_links.txt
frase.egg-info/entry_points.txt
frase.egg-info/requires.txt
frase.egg-info/top_level.txt
frase.egg-info/zip-safe
frase/api/__init__.py
frase/api/appbuilder.py
frase/api/main.py
frase/api/middleware.py
frase/api/router.py
frase/api/resources/__init__.py
frase/api/resources/generation.py
frase/api/resources/info.py
frase/frase_selenium/__init__.py
frase/frase_selenium/common.py
frase/frase_selenium/fraseio.py
frase/frase_selenium/fraseio_paths.py
tests/__init__.py
tests/api/__init__.py
tests/api/base.py
tests/api/resources/__init__.py
tests/api/resources/test_generation.py
tests/api/resources/test_info.py
tests/frase_selenium/__init__.py
tests/frase_selenium/test_fraseio.py