Metadata-Version: 2.1
Name: frase
Version: 0.0.5
Summary: TWNTY Frase API
Home-page: UNKNOWN
Author: Kristina Kurhanska
Author-email: kurganska@twnty.de
License: UNKNOWN
Platform: UNKNOWN
License-File: LICENSE.txt
